justrun/__init__.py
justrun-0.1.0.dist-info/LICENSE
justrun-0.1.0.dist-info/METADATA
justrun-0.1.0.dist-info/WHEEL
justrun-0.1.0.dist-info/top_level.txt
justrun-0.1.0.dist-info/RECORD
