Metadata-Version: 2.1
Name: justrun
Version: 0.1.0
Summary: The simplest way to enable multiple python environment work togather. 
Home-page: https://github.com/Buggist/Just-Run
Author: buggist
Author-email: 316114933@qq.com
Classifier: Programming Language :: Python :: 3
Classifier: License :: OSI Approved :: MIT License
Classifier: Operating System :: OS Independent
License-File: LICENSE
